yggdrasilctl/__init__.py
yggdrasilctl/aio.py
yggdrasilctl/errors.py
yggdrasilctl/sync.py
yggdrasilctl/utils.py
yggdrasilctl-0.0.1a4.dist-info/LICENSE
yggdrasilctl-0.0.1a4.dist-info/METADATA
yggdrasilctl-0.0.1a4.dist-info/WHEEL
yggdrasilctl-0.0.1a4.dist-info/top_level.txt
yggdrasilctl-0.0.1a4.dist-info/RECORD
