Metadata-Version: 2.1
Name: yggdrasilctl
Version: 0.0.1a4
Summary: Wrapper for Yggdrasil Admin API
Home-page: https://github.com/jorektheglitch/yggdrasilctl
Author: jorektheglitch
Author-email: jorektheglitch@yandex.ru
License: UNKNOWN
Platform: UNKNOWN
Classifier: Programming Language :: Python :: 3
Classifier: Operating System :: OS Independent
Requires-Python: >=3.6
